{"history_past": [{"id": 7749, "season_name": "2017/18", "element_code": 66247, "start_cost": 45, "end_cost": 40, "total_points": 28, "minutes": 993, "goals_scored": 0, "assists": 2, "clean_sheets": 2, "goals_conceded": 18, "own_goals": 0, "penalties_saved": 0, "penalties_missed": 0, "yellow_cards": 4, "red_cards": 1, "saves": 0, "bonus": 5, "bps": 186, "influence": "185.2", "creativity": "142.1", "threat": "24.0", "ict_index": "35.2", "ea_index": 0, "season": 12}], "fixtures_summary": [{"id": 319, "kickoff_time_formatted": "30 Mar 15:00", "event_name": "Gameweek 32", "opponent_name": "Man Utd", "opponent_short_name": "MUN", "is_home": false, "difficulty": 4, "code": 987910, "kickoff_time": "2019-03-30T15:00:00Z", "team_h_score": null, "team_a_score": null, "finished": false, "minutes": 0, "provisional_start_time": false, "finished_provisional": false, "event": 32, "team_a": 18, "team_h": 14}, {"id": 329, "kickoff_time_formatted": "02 Apr 19:45", "event_name": "Gameweek 32", "opponent_name": "Fulham", "opponent_short_name": "FUL", "is_home": true, "difficulty": 2, "code": 987920, "kickoff_time": "2019-04-02T18:45:00Z", "team_h_score": null, "team_a_score": null, "finished": false, "minutes": 0, "provisional_start_time": false, "finished_provisional": false, "event": 32, "team_a": 9, "team_h": 18}, {"id": 340, "kickoff_time_formatted": "15 Apr 20:00", "event_name": "Gameweek 34", "opponent_name": "Arsenal", "opponent_short_name": "ARS", "is_home": true, "difficulty": 4, "code": 987931, "kickoff_time": "2019-04-15T19:00:00Z", "team_h_score": null, "team_a_score": null, "finished": false, "minutes": 0, "provisional_start_time": false, "finished_provisional": false, "event": 34, "team_a": 1, "team_h": 18}], "explain": [], "history_summary": [{"id": 15389, "kickoff_time": "2019-02-27T20:00:00Z", "kickoff_time_formatted": "27 Feb 20:00", "team_h_score": 5, "team_a_score": 0, "was_home": false, "round": 28, "total_points": 0, "value": 42, "transfers_balance": -16, "selected": 2902, "transfers_in": 1, "transfers_out": 17, "loaned_in": 0, "loaned_out": 0, "minutes": 0, "goals_scored": 0, "assists": 0, "clean_sheets": 0, "goals_conceded": 0, "own_goals": 0, "penalties_saved": 0, "penalties_missed": 0, "yellow_cards": 0, "red_cards": 0, "saves": 0, "bonus": 0, "bps": 0, "influence": "0.0", "creativity": "0.0", "threat": "0.0", "ict_index": "0.0", "ea_index": 0, "open_play_crosses": 0, "big_chances_created": 0, "clearances_blocks_interceptions": 0, "recoveries": 0, "key_passes": 0, "tackles": 0, "winning_goals": 0, "attempted_passes": 0, "completed_passes": 0, "penalties_conceded": 0, "big_chances_missed": 0, "errors_leading_to_goal": 0, "errors_leading_to_goal_attempt": 0, "tackled": 0, "offside": 0, "target_missed": 0, "fouls": 0, "dribbles": 0, "element": 384, "fixture": 277, "opponent_team": 12}, {"id": 15994, "kickoff_time": "2019-03-03T12:00:00Z", "kickoff_time_formatted": "03 Mar 12:00", "team_h_score": 2, "team_a_score": 1, "was_home": true, "round": 29, "total_points": 0, "value": 42, "transfers_balance": -14, "selected": 2891, "transfers_in": 1, "transfers_out": 15, "loaned_in": 0, "loaned_out": 0, "minutes": 0, "goals_scored": 0, "assists": 0, "clean_sheets": 0, "goals_conceded": 0, "own_goals": 0, "penalties_saved": 0, "penalties_missed": 0, "yellow_cards": 0, "red_cards": 0, "saves": 0, "bonus": 0, "bps": 0, "influence": "0.0", "creativity": "0.0", "threat": "0.0", "ict_index": "0.0", "ea_index": 0, "open_play_crosses": 0, "big_chances_created": 0, "clearances_blocks_interceptions": 0, "recoveries": 0, "key_passes": 0, "tackles": 0, "winning_goals": 0, "attempted_passes": 0, "completed_passes": 0, "penalties_conceded": 0, "big_chances_missed": 0, "errors_leading_to_goal": 0, "errors_leading_to_goal_attempt": 0, "tackled": 0, "offside": 0, "target_missed": 0, "fouls": 0, "dribbles": 0, "element": 384, "fixture": 288, "opponent_team": 11}, {"id": 16600, "kickoff_time": "2019-03-09T17:30:00Z", "kickoff_time_formatted": "09 Mar 17:30", "team_h_score": 3, "team_a_score": 1, "was_home": false, "round": 30, "total_points": 0, "value": 42, "transfers_balance": -25, "selected": 2864, "transfers_in": 0, "transfers_out": 25, "loaned_in": 0, "loaned_out": 0, "minutes": 0, "goals_scored": 0, "assists": 0, "clean_sheets": 0, "goals_conceded": 0, "own_goals": 0, "penalties_saved": 0, "penalties_missed": 0, "yellow_cards": 0, "red_cards": 0, "saves": 0, "bonus": 0, "bps": 0, "influence": "0.0", "creativity": "0.0", "threat": "0.0", "ict_index": "0.0", "ea_index": 0, "open_play_crosses": 0, "big_chances_created": 0, "clearances_blocks_interceptions": 0, "recoveries": 0, "key_passes": 0, "tackles": 0, "winning_goals": 0, "attempted_passes": 0, "completed_passes": 0, "penalties_conceded": 0, "big_chances_missed": 0, "errors_leading_to_goal": 0, "errors_leading_to_goal_attempt": 0, "tackled": 0, "offside": 0, "target_missed": 0, "fouls": 0, "dribbles": 0, "element": 384, "fixture": 298, "opponent_team": 13}], "fixtures": [{"id": 319, "kickoff_time_formatted": "30 Mar 15:00", "event_name": "Gameweek 32", "opponent_name": "Man Utd", "opponent_short_name": "MUN", "is_home": false, "difficulty": 4, "code": 987910, "kickoff_time": "2019-03-30T15:00:00Z", "team_h_score": null, "team_a_score": null, "finished": false, "minutes": 0, "provisional_start_time": false, "finished_provisional": false, "event": 32, "team_a": 18, "team_h": 14}, {"id": 329, "kickoff_time_formatted": "02 Apr 19:45", "event_name": "Gameweek 32", "opponent_name": "Fulham", "opponent_short_name": "FUL", "is_home": true, "difficulty": 2, "code": 987920, "kickoff_time": "2019-04-02T18:45:00Z", "team_h_score": null, "team_a_score": null, "finished": false, "minutes": 0, "provisional_start_time": false, "finished_provisional": false, "event": 32, "team_a": 9, "team_h": 18}, {"id": 340, "kickoff_time_formatted": "15 Apr 20:00", "event_name": "Gameweek 34", "opponent_name": "Arsenal", "opponent_short_name": "ARS", "is_home": true, "difficulty": 4, "code": 987931, "kickoff_time": "2019-04-15T19:00:00Z", "team_h_score": null, "team_a_score": null, "finished": false, "minutes": 0, "provisional_start_time": false, "finished_provisional": false, "event": 34, "team_a": 1, "team_h": 18}, {"id": 346, "kickoff_time_formatted": "20 Apr 15:00", "event_name": "Gameweek 35", "opponent_name": "Huddersfield", "opponent_short_name": "HUD", "is_home": false, "difficulty": 2, "code": 987937, "kickoff_time": "2019-04-20T14:00:00Z", "team_h_score": null, "team_a_score": null, "finished": false, "minutes": 0, "provisional_start_time": false, "finished_provisional": false, "event": 35, "team_a": 18, "team_h": 10}, {"id": 308, "kickoff_time_formatted": "23 Apr 19:45", "event_name": "Gameweek 35", "opponent_name": "Southampton", "opponent_short_name": "SOU", "is_home": true, "difficulty": 2, "code": 987899, "kickoff_time": "2019-04-23T18:45:00Z", "team_h_score": null, "team_a_score": null, "finished": false, "minutes": 0, "provisional_start_time": false, "finished_provisional": false, "event": 35, "team_a": 16, "team_h": 18}, {"id": 360, "kickoff_time_formatted": "27 Apr 15:00", "event_name": "Gameweek 36", "opponent_name": "Wolves", "opponent_short_name": "WOL", "is_home": true, "difficulty": 3, "code": 987951, "kickoff_time": "2019-04-27T14:00:00Z", "team_h_score": null, "team_a_score": null, "finished": false, "minutes": 0, "provisional_start_time": false, "finished_provisional": false, "event": 36, "team_a": 20, "team_h": 18}, {"id": 364, "kickoff_time_formatted": "04 May 15:00", "event_name": "Gameweek 37", "opponent_name": "Chelsea", "opponent_short_name": "CHE", "is_home": false, "difficulty": 4, "code": 987955, "kickoff_time": "2019-05-04T14:00:00Z", "team_h_score": null, "team_a_score": null, "finished": false, "minutes": 0, "provisional_start_time": false, "finished_provisional": false, "event": 37, "team_a": 18, "team_h": 6}, {"id": 380, "kickoff_time_formatted": "12 May 15:00", "event_name": "Gameweek 38", "opponent_name": "West Ham", "opponent_short_name": "WHU", "is_home": true, "difficulty": 3, "code": 987971, "kickoff_time": "2019-05-12T14:00:00Z", "team_h_score": null, "team_a_score": null, "finished": false, "minutes": 0, "provisional_start_time": false, "finished_provisional": false, "event": 38, "team_a": 19, "team_h": 18}], "history": [{"id": 384, "kickoff_time": "2018-08-11T14:00:00Z", "kickoff_time_formatted": "11 Aug 15:00", "team_h_score": 2, "team_a_score": 0, "was_home": true, "round": 1, "total_points": 0, "value": 45, "transfers_balance": 0, "selected": 5698, "transfers_in": 0, "transfers_out": 0, "loaned_in": 0, "loaned_out": 0, "minutes": 0, "goals_scored": 0, "assists": 0, "clean_sheets": 0, "goals_conceded": 0, "own_goals": 0, "penalties_saved": 0, "penalties_missed": 0, "yellow_cards": 0, "red_cards": 0, "saves": 0, "bonus": 0, "bps": 0, "influence": "0.0", "creativity": "0.0", "threat": "0.0", "ict_index": "0.0", "ea_index": 0, "open_play_crosses": 0, "big_chances_created": 0, "clearances_blocks_interceptions": 0, "recoveries": 0, "key_passes": 0, "tackles": 0, "winning_goals": 0, "attempted_passes": 0, "completed_passes": 0, "penalties_conceded": 0, "big_chances_missed": 0, "errors_leading_to_goal": 0, "errors_leading_to_goal_attempt": 0, "tackled": 0, "offside": 0, "target_missed": 0, "fouls": 0, "dribbles": 0, "element": 384, "fixture": 9, "opponent_team": 3}, {"id": 909, "kickoff_time": "2018-08-19T12:30:00Z", "kickoff_time_formatted": "19 Aug 13:30", "team_h_score": 1, "team_a_score": 3, "was_home": false, "round": 2, "total_points": 0, "value": 45, "transfers_balance": -946, "selected": 5223, "transfers_in": 59, "transfers_out": 1005, "loaned_in": 0, "loaned_out": 0, "minutes": 0, "goals_scored": 0, "assists": 0, "clean_sheets": 0, "goals_conceded": 0, "own_goals": 0, "penalties_saved": 0, "penalties_missed": 0, "yellow_cards": 0, "red_cards": 0, "saves": 0, "bonus": 0, "bps": 0, "influence": "0.0", "creativity": "0.0", "threat": "0.0", "ict_index": "0.0", "ea_index": 0, "open_play_crosses": 0, "big_chances_created": 0, "clearances_blocks_interceptions": 0, "recoveries": 0, "key_passes": 0, "tackles": 0, "winning_goals": 0, "attempted_passes": 0, "completed_passes": 0, "penalties_conceded": 0, "big_chances_missed": 0, "errors_leading_to_goal": 0, "errors_leading_to_goal_attempt": 0, "tackled": 0, "offside": 0, "target_missed": 0, "fouls": 0, "dribbles": 0, "element": 384, "fixture": 12, "opponent_team": 4}, {"id": 1436, "kickoff_time": "2018-08-26T12:30:00Z", "kickoff_time_formatted": "26 Aug 13:30", "team_h_score": 2, "team_a_score": 1, "was_home": true, "round": 3, "total_points": 0, "value": 44, "transfers_balance": -714, "selected": 4658, "transfers_in": 76, "transfers_out": 790, "loaned_in": 0, "loaned_out": 0, "minutes": 0, "goals_scored": 0, "assists": 0, "clean_sheets": 0, "goals_conceded": 0, "own_goals": 0, "penalties_saved": 0, "penalties_missed": 0, "yellow_cards": 0, "red_cards": 0, "saves": 0, "bonus": 0, "bps": 0, "influence": "0.0", "creativity": "0.0", "threat": "0.0", "ict_index": "0.0", "ea_index": 0, "open_play_crosses": 0, "big_chances_created": 0, "clearances_blocks_interceptions": 0, "recoveries": 0, "key_passes": 0, "tackles": 0, "winning_goals": 0, "attempted_passes": 0, "completed_passes": 0, "penalties_conceded": 0, "big_chances_missed": 0, "errors_leading_to_goal": 0, "errors_leading_to_goal_attempt": 0, "tackled": 0, "offside": 0, "target_missed": 0, "fouls": 0, "dribbles": 0, "element": 384, "fixture": 29, "opponent_team": 7}, {"id": 1967, "kickoff_time": "2018-09-02T15:00:00Z", "kickoff_time_formatted": "02 Sep 16:00", "team_h_score": 2, "team_a_score": 1, "was_home": true, "round": 4, "total_points": 0, "value": 44, "transfers_balance": -482, "selected": 4234, "transfers_in": 43, "transfers_out": 525, "loaned_in": 0, "loaned_out": 0, "minutes": 0, "goals_scored": 0, "assists": 0, "clean_sheets": 0, "goals_conceded": 0, "own_goals": 0, "penalties_saved": 0, "penalties_missed": 0, "yellow_cards": 0, "red_cards": 0, "saves": 0, "bonus": 0, "bps": 0, "influence": "0.0", "creativity": "0.0", "threat": "0.0", "ict_index": "0.0", "ea_index": 0, "open_play_crosses": 0, "big_chances_created": 0, "clearances_blocks_interceptions": 0, "recoveries": 0, "key_passes": 0, "tackles": 0, "winning_goals": 0, "attempted_passes": 0, "completed_passes": 0, "penalties_conceded": 0, "big_chances_missed": 0, "errors_leading_to_goal": 0, "errors_leading_to_goal_attempt": 0, "tackled": 0, "offside": 0, "target_missed": 0, "fouls": 0, "dribbles": 0, "element": 384, "fixture": 39, "opponent_team": 17}, {"id": 2504, "kickoff_time": "2018-09-15T16:30:00Z", "kickoff_time_formatted": "15 Sep 17:30", "team_h_score": 1, "team_a_score": 2, "was_home": true, "round": 5, "total_points": 0, "value": 43, "transfers_balance": -364, "selected": 3933, "transfers_in": 36, "transfers_out": 400, "loaned_in": 0, "loaned_out": 0, "minutes": 0, "goals_scored": 0, "assists": 0, "clean_sheets": 0, "goals_conceded": 0, "own_goals": 0, "penalties_saved": 0, "penalties_missed": 0, "yellow_cards": 0, "red_cards": 0, "saves": 0, "bonus": 0, "bps": 0, "influence": "0.0", "creativity": "0.0", "threat": "0.0", "ict_index": "0.0", "ea_index": 0, "open_play_crosses": 0, "big_chances_created": 0, "clearances_blocks_interceptions": 0, "recoveries": 0, "key_passes": 0, "tackles": 0, "winning_goals": 0, "attempted_passes": 0, "completed_passes": 0, "penalties_conceded": 0, "big_chances_missed": 0, "errors_leading_to_goal": 0, "errors_leading_to_goal_attempt": 0, "tackled": 0, "offside": 0, "target_missed": 0, "fouls": 0, "dribbles": 0, "element": 384, "fixture": 49, "opponent_team": 14}, {"id": 3041, "kickoff_time": "2018-09-22T11:30:00Z", "kickoff_time_formatted": "22 Sep 12:30", "team_h_score": 1, "team_a_score": 1, "was_home": false, "round": 6, "total_points": 0, "value": 43, "transfers_balance": -179, "selected": 3811, "transfers_in": 49, "transfers_out": 228, "loaned_in": 0, "loaned_out": 0, "minutes": 0, "goals_scored": 0, "assists": 0, "clean_sheets": 0, "goals_conceded": 0, "own_goals": 0, "penalties_saved": 0, "penalties_missed": 0, "yellow_cards": 0, "red_cards": 0, "saves": 0, "bonus": 0, "bps": 0, "influence": "0.0", "creativity": "0.0", "threat": "0.0", "ict_index": "0.0", "ea_index": 0, "open_play_crosses": 0, "big_chances_created": 0, "clearances_blocks_interceptions": 0, "recoveries": 0, "key_passes": 0, "tackles": 0, "winning_goals": 0, "attempted_passes": 0, "completed_passes": 0, "penalties_conceded": 0, "big_chances_missed": 0, "errors_leading_to_goal": 0, "errors_leading_to_goal_attempt": 0, "tackled": 0, "offside": 0, "target_missed": 0, "fouls": 0, "dribbles": 0, "element": 384, "fixture": 56, "opponent_team": 9}, {"id": 3579, "kickoff_time": "2018-09-29T14:00:00Z", "kickoff_time_formatted": "29 Sep 15:00", "team_h_score": 2, "team_a_score": 0, "was_home": false, "round": 7, "total_points": 0, "value": 43, "transfers_balance": -160, "selected": 3672, "transfers_in": 29, "transfers_out": 189, "loaned_in": 0, "loaned_out": 0, "minutes": 0, "goals_scored": 0, "assists": 0, "clean_sheets": 0, "goals_conceded": 0, "own_goals": 0, "penalties_saved": 0, "penalties_missed": 0, "yellow_cards": 0, "red_cards": 0, "saves": 0, "bonus": 0, "bps": 0, "influence": "0.0", "creativity": "0.0", "threat": "0.0", "ict_index": "0.0", "ea_index": 0, "open_play_crosses": 0, "big_chances_created": 0, "clearances_blocks_interceptions": 0, "recoveries": 0, "key_passes": 0, "tackles": 0, "winning_goals": 0, "attempted_passes": 0, "completed_passes": 0, "penalties_conceded": 0, "big_chances_missed": 0, "errors_leading_to_goal": 0, "errors_leading_to_goal_attempt": 0, "tackled": 0, "offside": 0, "target_missed": 0, "fouls": 0, "dribbles": 0, "element": 384, "fixture": 61, "opponent_team": 1}, {"id": 4118, "kickoff_time": "2018-10-06T14:00:00Z", "kickoff_time_formatted": "06 Oct 15:00", "team_h_score": 0, "team_a_score": 4, "was_home": true, "round": 8, "total_points": 0, "value": 43, "transfers_balance": -96, "selected": 3597, "transfers_in": 35, "transfers_out": 131, "loaned_in": 0, "loaned_out": 0, "minutes": 0, "goals_scored": 0, "assists": 0, "clean_sheets": 0, "goals_conceded": 0, "own_goals": 0, "penalties_saved": 0, "penalties_missed": 0, "yellow_cards": 0, "red_cards": 0, "saves": 0, "bonus": 0, "bps": 0, "influence": "0.0", "creativity": "0.0", "threat": "0.0", "ict_index": "0.0", "ea_index": 0, "open_play_crosses": 0, "big_chances_created": 0, "clearances_blocks_interceptions": 0, "recoveries": 0, "key_passes": 0, "tackles": 0, "winning_goals": 0, "attempted_passes": 0, "completed_passes": 0, "penalties_conceded": 0, "big_chances_missed": 0, "errors_leading_to_goal": 0, "errors_leading_to_goal_attempt": 0, "tackled": 0, "offside": 0, "target_missed": 0, "fouls": 0, "dribbles": 0, "element": 384, "fixture": 80, "opponent_team": 2}, {"id": 4660, "kickoff_time": "2018-10-20T14:00:00Z", "kickoff_time_formatted": "20 Oct 15:00", "team_h_score": 0, "team_a_score": 2, "was_home": false, "round": 9, "total_points": 0, "value": 43, "transfers_balance": -96, "selected": 3514, "transfers_in": 33, "transfers_out": 129, "loaned_in": 0, "loaned_out": 0, "minutes": 0, "goals_scored": 0, "assists": 0, "clean_sheets": 0, "goals_conceded": 0, "own_goals": 0, "penalties_saved": 0, "penalties_missed": 0, "yellow_cards": 0, "red_cards": 0, "saves": 0, "bonus": 0, "bps": 0, "influence": "0.0", "creativity": "0.0", "threat": "0.0", "ict_index": "0.0", "ea_index": 0, "open_play_crosses": 0, "big_chances_created": 0, "clearances_blocks_interceptions": 0, "recoveries": 0, "key_passes": 0, "tackles": 0, "winning_goals": 0, "attempted_passes": 0, "completed_passes": 0, "penalties_conceded": 0, "big_chances_missed": 0, "errors_leading_to_goal": 0, "errors_leading_to_goal_attempt": 0, "tackled": 0, "offside": 0, "target_missed": 0, "fouls": 0, "dribbles": 0, "element": 384, "fixture": 90, "opponent_team": 20}, {"id": 5206, "kickoff_time": "2018-10-27T14:00:00Z", "kickoff_time_formatted": "27 Oct 15:00", "team_h_score": 3, "team_a_score": 0, "was_home": true, "round": 10, "total_points": 0, "value": 43, "transfers_balance": -66, "selected": 3457, "transfers_in": 29, "transfers_out": 95, "loaned_in": 0, "loaned_out": 0, "minutes": 0, "goals_scored": 0, "assists": 0, "clean_sheets": 0, "goals_conceded": 0, "own_goals": 0, "penalties_saved": 0, "penalties_missed": 0, "yellow_cards": 0, "red_cards": 0, "saves": 0, "bonus": 0, "bps": 0, "influence": "0.0", "creativity": "0.0", "threat": "0.0", "ict_index": "0.0", "ea_index": 0, "open_play_crosses": 0, "big_chances_created": 0, "clearances_blocks_interceptions": 0, "recoveries": 0, "key_passes": 0, "tackles": 0, "winning_goals": 0, "attempted_passes": 0, "completed_passes": 0, "penalties_conceded": 0, "big_chances_missed": 0, "errors_leading_to_goal": 0, "errors_leading_to_goal_attempt": 0, "tackled": 0, "offside": 0, "target_missed": 0, "fouls": 0, "dribbles": 0, "element": 384, "fixture": 100, "opponent_team": 10}, {"id": 5754, "kickoff_time": "2018-11-03T15:00:00Z", "kickoff_time_formatted": "03 Nov 15:00", "team_h_score": 1, "team_a_score": 0, "was_home": false, "round": 11, "total_points": 0, "value": 42, "transfers_balance": -36, "selected": 3451, "transfers_in": 75, "transfers_out": 111, "loaned_in": 0, "loaned_out": 0, "minutes": 0, "goals_scored": 0, "assists": 0, "clean_sheets": 0, "goals_conceded": 0, "own_goals": 0, "penalties_saved": 0, "penalties_missed": 0, "yellow_cards": 0, "red_cards": 0, "saves": 0, "bonus": 0, "bps": 0, "influence": "0.0", "creativity": "0.0", "threat": "0.0", "ict_index": "0.0", "ea_index": 0, "open_play_crosses": 0, "big_chances_created": 0, "clearances_blocks_interceptions": 0, "recoveries": 0, "key_passes": 0, "tackles": 0, "winning_goals": 0, "attempted_passes": 0, "completed_passes": 0, "penalties_conceded": 0, "big_chances_missed": 0, "errors_leading_to_goal": 0, "errors_leading_to_goal_attempt": 0, "tackled": 0, "offside": 0, "target_missed": 0, "fouls": 0, "dribbles": 0, "element": 384, "fixture": 108, "opponent_team": 15}, {"id": 6304, "kickoff_time": "2018-11-10T15:00:00Z", "kickoff_time_formatted": "10 Nov 15:00", "team_h_score": 1, "team_a_score": 1, "was_home": false, "round": 12, "total_points": 0, "value": 42, "transfers_balance": -52, "selected": 3415, "transfers_in": 49, "transfers_out": 101, "loaned_in": 0, "loaned_out": 0, "minutes": 0, "goals_scored": 0, "assists": 0, "clean_sheets": 0, "goals_conceded": 0, "own_goals": 0, "penalties_saved": 0, "penalties_missed": 0, "yellow_cards": 0, "red_cards": 0, "saves": 0, "bonus": 0, "bps": 0, "influence": "0.0", "creativity": "0.0", "threat": "0.0", "ict_index": "0.0", "ea_index": 0, "open_play_crosses": 0, "big_chances_created": 0, "clearances_blocks_interceptions": 0, "recoveries": 0, "key_passes": 0, "tackles": 0, "winning_goals": 0, "attempted_passes": 0, "completed_passes": 0, "penalties_conceded": 0, "big_chances_missed": 0, "errors_leading_to_goal": 0, "errors_leading_to_goal_attempt": 0, "tackled": 0, "offside": 0, "target_missed": 0, "fouls": 0, "dribbles": 0, "element": 384, "fixture": 120, "opponent_team": 16}, {"id": 6856, "kickoff_time": "2018-11-24T15:00:00Z", "kickoff_time_formatted": "24 Nov 15:00", "team_h_score": 0, "team_a_score": 3, "was_home": true, "round": 13, "total_points": 0, "value": 42, "transfers_balance": -32, "selected": 3407, "transfers_in": 52, "transfers_out": 84, "loaned_in": 0, "loaned_out": 0, "minutes": 0, "goals_scored": 0, "assists": 0, "clean_sheets": 0, "goals_conceded": 0, "own_goals": 0, "penalties_saved": 0, "penalties_missed": 0, "yellow_cards": 0, "red_cards": 0, "saves": 0, "bonus": 0, "bps": 0, "influence": "0.0", "creativity": "0.0", "threat": "0.0", "ict_index": "0.0", "ea_index": 0, "open_play_crosses": 0, "big_chances_created": 0, "clearances_blocks_interceptions": 0, "recoveries": 0, "key_passes": 0, "tackles": 0, "winning_goals": 0, "attempted_passes": 0, "completed_passes": 0, "penalties_conceded": 0, "big_chances_missed": 0, "errors_leading_to_goal": 0, "errors_leading_to_goal_attempt": 0, "tackled": 0, "offside": 0, "target_missed": 0, "fouls": 0, "dribbles": 0, "element": 384, "fixture": 128, "opponent_team": 12}, {"id": 7409, "kickoff_time": "2018-12-01T15:00:00Z", "kickoff_time_formatted": "01 Dec 15:00", "team_h_score": 2, "team_a_score": 0, "was_home": false, "round": 14, "total_points": 0, "value": 42, "transfers_balance": -21, "selected": 3396, "transfers_in": 30, "transfers_out": 51, "loaned_in": 0, "loaned_out": 0, "minutes": 0, "goals_scored": 0, "assists": 0, "clean_sheets": 0, "goals_conceded": 0, "own_goals": 0, "penalties_saved": 0, "penalties_missed": 0, "yellow_cards": 0, "red_cards": 0, "saves": 0, "bonus": 0, "bps": 0, "influence": "0.0", "creativity": "0.0", "threat": "0.0", "ict_index": "0.0", "ea_index": 0, "open_play_crosses": 0, "big_chances_created": 0, "clearances_blocks_interceptions": 0, "recoveries": 0, "key_passes": 0, "tackles": 0, "winning_goals": 0, "attempted_passes": 0, "completed_passes": 0, "penalties_conceded": 0, "big_chances_missed": 0, "errors_leading_to_goal": 0, "errors_leading_to_goal_attempt": 0, "tackled": 0, "offside": 0, "target_missed": 0, "fouls": 0, "dribbles": 0, "element": 384, "fixture": 136, "opponent_team": 11}, {"id": 7965, "kickoff_time": "2018-12-04T20:00:00Z", "kickoff_time_formatted": "04 Dec 20:00", "team_h_score": 1, "team_a_score": 2, "was_home": true, "round": 15, "total_points": 0, "value": 42, "transfers_balance": -32, "selected": 3369, "transfers_in": 20, "transfers_out": 52, "loaned_in": 0, "loaned_out": 0, "minutes": 0, "goals_scored": 0, "assists": 0, "clean_sheets": 0, "goals_conceded": 0, "own_goals": 0, "penalties_saved": 0, "penalties_missed": 0, "yellow_cards": 0, "red_cards": 0, "saves": 0, "bonus": 0, "bps": 0, "influence": "0.0", "creativity": "0.0", "threat": "0.0", "ict_index": "0.0", "ea_index": 0, "open_play_crosses": 0, "big_chances_created": 0, "clearances_blocks_interceptions": 0, "recoveries": 0, "key_passes": 0, "tackles": 0, "winning_goals": 0, "attempted_passes": 0, "completed_passes": 0, "penalties_conceded": 0, "big_chances_missed": 0, "errors_leading_to_goal": 0, "errors_leading_to_goal_attempt": 0, "tackled": 0, "offside": 0, "target_missed": 0, "fouls": 0, "dribbles": 0, "element": 384, "fixture": 146, "opponent_team": 13}, {"id": 8523, "kickoff_time": "2018-12-10T20:00:00Z", "kickoff_time_formatted": "10 Dec 20:00", "team_h_score": 2, "team_a_score": 2, "was_home": false, "round": 16, "total_points": 0, "value": 42, "transfers_balance": -32, "selected": 3349, "transfers_in": 21, "transfers_out": 53, "loaned_in": 0, "loaned_out": 0, "minutes": 0, "goals_scored": 0, "assists": 0, "clean_sheets": 0, "goals_conceded": 0, "own_goals": 0, "penalties_saved": 0, "penalties_missed": 0, "yellow_cards": 0, "red_cards": 0, "saves": 0, "bonus": 0, "bps": 0, "influence": "0.0", "creativity": "0.0", "threat": "0.0", "ict_index": "0.0", "ea_index": 0, "open_play_crosses": 0, "big_chances_created": 0, "clearances_blocks_interceptions": 0, "recoveries": 0, "key_passes": 0, "tackles": 0, "winning_goals": 0, "attempted_passes": 0, "completed_passes": 0, "penalties_conceded": 0, "big_chances_missed": 0, "errors_leading_to_goal": 0, "errors_leading_to_goal_attempt": 0, "tackled": 0, "offside": 0, "target_missed": 0, "fouls": 0, "dribbles": 0, "element": 384, "fixture": 156, "opponent_team": 8}, {"id": 9082, "kickoff_time": "2018-12-15T15:00:00Z", "kickoff_time_formatted": "15 Dec 15:00", "team_h_score": 3, "team_a_score": 2, "was_home": true, "round": 17, "total_points": 0, "value": 42, "transfers_balance": -29, "selected": 3336, "transfers_in": 33, "transfers_out": 62, "loaned_in": 0, "loaned_out": 0, "minutes": 0, "goals_scored": 0, "assists": 0, "clean_sheets": 0, "goals_conceded": 0, "own_goals": 0, "penalties_saved": 0, "penalties_missed": 0, "yellow_cards": 0, "red_cards": 0, "saves": 0, "bonus": 0, "bps": 0, "influence": "0.0", "creativity": "0.0", "threat": "0.0", "ict_index": "0.0", "ea_index": 0, "open_play_crosses": 0, "big_chances_created": 0, "clearances_blocks_interceptions": 0, "recoveries": 0, "key_passes": 0, "tackles": 0, "winning_goals": 0, "attempted_passes": 0, "completed_passes": 0, "penalties_conceded": 0, "big_chances_missed": 0, "errors_leading_to_goal": 0, "errors_leading_to_goal_attempt": 0, "tackled": 0, "offside": 0, "target_missed": 0, "fouls": 0, "dribbles": 0, "element": 384, "fixture": 169, "opponent_team": 5}, {"id": 9644, "kickoff_time": "2018-12-22T15:00:00Z", "kickoff_time_formatted": "22 Dec 15:00", "team_h_score": 0, "team_a_score": 2, "was_home": false, "round": 18, "total_points": 0, "value": 42, "transfers_balance": -26, "selected": 3316, "transfers_in": 30, "transfers_out": 56, "loaned_in": 0, "loaned_out": 0, "minutes": 0, "goals_scored": 0, "assists": 0, "clean_sheets": 0, "goals_conceded": 0, "own_goals": 0, "penalties_saved": 0, "penalties_missed": 0, "yellow_cards": 0, "red_cards": 0, "saves": 0, "bonus": 0, "bps": 0, "influence": "0.0", "creativity": "0.0", "threat": "0.0", "ict_index": "0.0", "ea_index": 0, "open_play_crosses": 0, "big_chances_created": 0, "clearances_blocks_interceptions": 0, "recoveries": 0, "key_passes": 0, "tackles": 0, "winning_goals": 0, "attempted_passes": 0, "completed_passes": 0, "penalties_conceded": 0, "big_chances_missed": 0, "errors_leading_to_goal": 0, "errors_leading_to_goal_attempt": 0, "tackled": 0, "offside": 0, "target_missed": 0, "fouls": 0, "dribbles": 0, "element": 384, "fixture": 179, "opponent_team": 19}, {"id": 10209, "kickoff_time": "2018-12-26T19:30:00Z", "kickoff_time_formatted": "26 Dec 19:30", "team_h_score": 1, "team_a_score": 2, "was_home": true, "round": 19, "total_points": 0, "value": 42, "transfers_balance": -2, "selected": 3373, "transfers_in": 56, "transfers_out": 58, "loaned_in": 0, "loaned_out": 0, "minutes": 0, "goals_scored": 0, "assists": 0, "clean_sheets": 0, "goals_conceded": 0, "own_goals": 0, "penalties_saved": 0, "penalties_missed": 0, "yellow_cards": 0, "red_cards": 0, "saves": 0, "bonus": 0, "bps": 0, "influence": "0.0", "creativity": "0.0", "threat": "0.0", "ict_index": "0.0", "ea_index": 0, "open_play_crosses": 0, "big_chances_created": 0, "clearances_blocks_interceptions": 0, "recoveries": 0, "key_passes": 0, "tackles": 0, "winning_goals": 0, "attempted_passes": 0, "completed_passes": 0, "penalties_conceded": 0, "big_chances_missed": 0, "errors_leading_to_goal": 0, "errors_leading_to_goal_attempt": 0, "tackled": 0, "offside": 0, "target_missed": 0, "fouls": 0, "dribbles": 0, "element": 384, "fixture": 190, "opponent_team": 6}, {"id": 10777, "kickoff_time": "2018-12-29T15:00:00Z", "kickoff_time_formatted": "29 Dec 15:00", "team_h_score": 1, "team_a_score": 1, "was_home": true, "round": 20, "total_points": 0, "value": 42, "transfers_balance": -9, "selected": 3368, "transfers_in": 58, "transfers_out": 67, "loaned_in": 0, "loaned_out": 0, "minutes": 0, "goals_scored": 0, "assists": 0, "clean_sheets": 0, "goals_conceded": 0, "own_goals": 0, "penalties_saved": 0, "penalties_missed": 0, "yellow_cards": 0, "red_cards": 0, "saves": 0, "bonus": 0, "bps": 0, "influence": "0.0", "creativity": "0.0", "threat": "0.0", "ict_index": "0.0", "ea_index": 0, "open_play_crosses": 0, "big_chances_created": 0, "clearances_blocks_interceptions": 0, "recoveries": 0, "key_passes": 0, "tackles": 0, "winning_goals": 0, "attempted_passes": 0, "completed_passes": 0, "penalties_conceded": 0, "big_chances_missed": 0, "errors_leading_to_goal": 0, "errors_leading_to_goal_attempt": 0, "tackled": 0, "offside": 0, "target_missed": 0, "fouls": 0, "dribbles": 0, "element": 384, "fixture": 200, "opponent_team": 15}, {"id": 11345, "kickoff_time": "2019-01-02T19:45:00Z", "kickoff_time_formatted": "02 Jan 19:45", "team_h_score": 3, "team_a_score": 3, "was_home": false, "round": 21, "total_points": 0, "value": 42, "transfers_balance": -13, "selected": 3371, "transfers_in": 63, "transfers_out": 76, "loaned_in": 0, "loaned_out": 0, "minutes": 0, "goals_scored": 0, "assists": 0, "clean_sheets": 0, "goals_conceded": 0, "own_goals": 0, "penalties_saved": 0, "penalties_missed": 0, "yellow_cards": 0, "red_cards": 0, "saves": 0, "bonus": 0, "bps": 0, "influence": "0.0", "creativity": "0.0", "threat": "0.0", "ict_index": "0.0", "ea_index": 0, "open_play_crosses": 0, "big_chances_created": 0, "clearances_blocks_interceptions": 0, "recoveries": 0, "key_passes": 0, "tackles": 0, "winning_goals": 0, "attempted_passes": 0, "completed_passes": 0, "penalties_conceded": 0, "big_chances_missed": 0, "errors_leading_to_goal": 0, "errors_leading_to_goal_attempt": 0, "tackled": 0, "offside": 0, "target_missed": 0, "fouls": 0, "dribbles": 0, "element": 384, "fixture": 202, "opponent_team": 2}, {"id": 11915, "kickoff_time": "2019-01-12T15:00:00Z", "kickoff_time_formatted": "12 Jan 15:00", "team_h_score": 1, "team_a_score": 2, "was_home": false, "round": 22, "total_points": 0, "value": 42, "transfers_balance": -70, "selected": 3314, "transfers_in": 60, "transfers_out": 130, "loaned_in": 0, "loaned_out": 0, "minutes": 0, "goals_scored": 0, "assists": 0, "clean_sheets": 0, "goals_conceded": 0, "own_goals": 0, "penalties_saved": 0, "penalties_missed": 0, "yellow_cards": 0, "red_cards": 0, "saves": 0, "bonus": 0, "bps": 0, "influence": "0.0", "creativity": "0.0", "threat": "0.0", "ict_index": "0.0", "ea_index": 0, "open_play_crosses": 0, "big_chances_created": 0, "clearances_blocks_interceptions": 0, "recoveries": 0, "key_passes": 0, "tackles": 0, "winning_goals": 0, "attempted_passes": 0, "completed_passes": 0, "penalties_conceded": 0, "big_chances_missed": 0, "errors_leading_to_goal": 0, "errors_leading_to_goal_attempt": 0, "tackled": 0, "offside": 0, "target_missed": 0, "fouls": 0, "dribbles": 0, "element": 384, "fixture": 215, "opponent_team": 7}, {"id": 12489, "kickoff_time": "2019-01-19T15:00:00Z", "kickoff_time_formatted": "19 Jan 15:00", "team_h_score": 0, "team_a_score": 0, "was_home": true, "round": 23, "total_points": 0, "value": 42, "transfers_balance": -160, "selected": 3150, "transfers_in": 19, "transfers_out": 179, "loaned_in": 0, "loaned_out": 0, "minutes": 0, "goals_scored": 0, "assists": 0, "clean_sheets": 0, "goals_conceded": 0, "own_goals": 0, "penalties_saved": 0, "penalties_missed": 0, "yellow_cards": 0, "red_cards": 0, "saves": 0, "bonus": 0, "bps": 0, "influence": "0.0", "creativity": "0.0", "threat": "0.0", "ict_index": "0.0", "ea_index": 0, "open_play_crosses": 0, "big_chances_created": 0, "clearances_blocks_interceptions": 0, "recoveries": 0, "key_passes": 0, "tackles": 0, "winning_goals": 0, "attempted_passes": 0, "completed_passes": 0, "penalties_conceded": 0, "big_chances_missed": 0, "errors_leading_to_goal": 0, "errors_leading_to_goal_attempt": 0, "tackled": 0, "offside": 0, "target_missed": 0, "fouls": 0, "dribbles": 0, "element": 384, "fixture": 229, "opponent_team": 4}, {"id": 13068, "kickoff_time": "2019-01-30T20:00:00Z", "kickoff_time_formatted": "30 Jan 20:00", "team_h_score": 2, "team_a_score": 1, "was_home": false, "round": 24, "total_points": 0, "value": 42, "transfers_balance": -99, "selected": 3061, "transfers_in": 3, "transfers_out": 102, "loaned_in": 0, "loaned_out": 0, "minutes": 0, "goals_scored": 0, "assists": 0, "clean_sheets": 0, "goals_conceded": 0, "own_goals": 0, "penalties_saved": 0, "penalties_missed": 0, "yellow_cards": 0, "red_cards": 0, "saves": 0, "bonus": 0, "bps": 0, "influence": "0.0", "creativity": "0.0", "threat": "0.0", "ict_index": "0.0", "ea_index": 0, "open_play_crosses": 0, "big_chances_created": 0, "clearances_blocks_interceptions": 0, "recoveries": 0, "key_passes": 0, "tackles": 0, "winning_goals": 0, "attempted_passes": 0, "completed_passes": 0, "penalties_conceded": 0, "big_chances_missed": 0, "errors_leading_to_goal": 0, "errors_leading_to_goal_attempt": 0, "tackled": 0, "offside": 0, "target_missed": 0, "fouls": 0, "dribbles": 0, "element": 384, "fixture": 240, "opponent_team": 17}, {"id": 13697, "kickoff_time": "2019-02-02T15:00:00Z", "kickoff_time_formatted": "02 Feb 15:00", "team_h_score": 0, "team_a_score": 0, "was_home": false, "round": 25, "total_points": 0, "value": 42, "transfers_balance": -34, "selected": 3023, "transfers_in": 1, "transfers_out": 35, "loaned_in": 0, "loaned_out": 0, "minutes": 0, "goals_scored": 0, "assists": 0, "clean_sheets": 0, "goals_conceded": 0, "own_goals": 0, "penalties_saved": 0, "penalties_missed": 0, "yellow_cards": 0, "red_cards": 0, "saves": 0, "bonus": 0, "bps": 0, "influence": "0.0", "creativity": "0.0", "threat": "0.0", "ict_index": "0.0", "ea_index": 0, "open_play_crosses": 0, "big_chances_created": 0, "clearances_blocks_interceptions": 0, "recoveries": 0, "key_passes": 0, "tackles": 0, "winning_goals": 0, "attempted_passes": 0, "completed_passes": 0, "penalties_conceded": 0, "big_chances_missed": 0, "errors_leading_to_goal": 0, "errors_leading_to_goal_attempt": 0, "tackled": 0, "offside": 0, "target_missed": 0, "fouls": 0, "dribbles": 0, "element": 384, "fixture": 241, "opponent_team": 3}, {"id": 14305, "kickoff_time": "2019-02-09T15:00:00Z", "kickoff_time_formatted": "09 Feb 15:00", "team_h_score": 1, "team_a_score": 0, "was_home": true, "round": 26, "total_points": 0, "value": 42, "transfers_balance": -58, "selected": 2969, "transfers_in": 1, "transfers_out": 59, "loaned_in": 0, "loaned_out": 0, "minutes": 0, "goals_scored": 0, "assists": 0, "clean_sheets": 0, "goals_conceded": 0, "own_goals": 0, "penalties_saved": 0, "penalties_missed": 0, "yellow_cards": 0, "red_cards": 0, "saves": 0, "bonus": 0, "bps": 0, "influence": "0.0", "creativity": "0.0", "threat": "0.0", "ict_index": "0.0", "ea_index": 0, "open_play_crosses": 0, "big_chances_created": 0, "clearances_blocks_interceptions": 0, "recoveries": 0, "key_passes": 0, "tackles": 0, "winning_goals": 0, "attempted_passes": 0, "completed_passes": 0, "penalties_conceded": 0, "big_chances_missed": 0, "errors_leading_to_goal": 0, "errors_leading_to_goal_attempt": 0, "tackled": 0, "offside": 0, "target_missed": 0, "fouls": 0, "dribbles": 0, "element": 384, "fixture": 259, "opponent_team": 8}, {"id": 14814, "kickoff_time": "2019-02-22T19:45:00Z", "kickoff_time_formatted": "22 Feb 19:45", "team_h_score": 1, "team_a_score": 5, "was_home": false, "round": 27, "total_points": 0, "value": 42, "transfers_balance": -51, "selected": 2916, "transfers_in": 2, "transfers_out": 53, "loaned_in": 0, "loaned_out": 0, "minutes": 0, "goals_scored": 0, "assists": 0, "clean_sheets": 0, "goals_conceded": 0, "own_goals": 0, "penalties_saved": 0, "penalties_missed": 0, "yellow_cards": 0, "red_cards": 0, "saves": 0, "bonus": 0, "bps": 0, "influence": "0.0", "creativity": "0.0", "threat": "0.0", "ict_index": "0.0", "ea_index": 0, "open_play_crosses": 0, "big_chances_created": 0, "clearances_blocks_interceptions": 0, "recoveries": 0, "key_passes": 0, "tackles": 0, "winning_goals": 0, "attempted_passes": 0, "completed_passes": 0, "penalties_conceded": 0, "big_chances_missed": 0, "errors_leading_to_goal": 0, "errors_leading_to_goal_attempt": 0, "tackled": 0, "offside": 0, "target_missed": 0, "fouls": 0, "dribbles": 0, "element": 384, "fixture": 264, "opponent_team": 5}, {"id": 15389, "kickoff_time": "2019-02-27T20:00:00Z", "kickoff_time_formatted": "27 Feb 20:00", "team_h_score": 5, "team_a_score": 0, "was_home": false, "round": 28, "total_points": 0, "value": 42, "transfers_balance": -16, "selected": 2902, "transfers_in": 1, "transfers_out": 17, "loaned_in": 0, "loaned_out": 0, "minutes": 0, "goals_scored": 0, "assists": 0, "clean_sheets": 0, "goals_conceded": 0, "own_goals": 0, "penalties_saved": 0, "penalties_missed": 0, "yellow_cards": 0, "red_cards": 0, "saves": 0, "bonus": 0, "bps": 0, "influence": "0.0", "creativity": "0.0", "threat": "0.0", "ict_index": "0.0", "ea_index": 0, "open_play_crosses": 0, "big_chances_created": 0, "clearances_blocks_interceptions": 0, "recoveries": 0, "key_passes": 0, "tackles": 0, "winning_goals": 0, "attempted_passes": 0, "completed_passes": 0, "penalties_conceded": 0, "big_chances_missed": 0, "errors_leading_to_goal": 0, "errors_leading_to_goal_attempt": 0, "tackled": 0, "offside": 0, "target_missed": 0, "fouls": 0, "dribbles": 0, "element": 384, "fixture": 277, "opponent_team": 12}, {"id": 15994, "kickoff_time": "2019-03-03T12:00:00Z", "kickoff_time_formatted": "03 Mar 12:00", "team_h_score": 2, "team_a_score": 1, "was_home": true, "round": 29, "total_points": 0, "value": 42, "transfers_balance": -14, "selected": 2891, "transfers_in": 1, "transfers_out": 15, "loaned_in": 0, "loaned_out": 0, "minutes": 0, "goals_scored": 0, "assists": 0, "clean_sheets": 0, "goals_conceded": 0, "own_goals": 0, "penalties_saved": 0, "penalties_missed": 0, "yellow_cards": 0, "red_cards": 0, "saves": 0, "bonus": 0, "bps": 0, "influence": "0.0", "creativity": "0.0", "threat": "0.0", "ict_index": "0.0", "ea_index": 0, "open_play_crosses": 0, "big_chances_created": 0, "clearances_blocks_interceptions": 0, "recoveries": 0, "key_passes": 0, "tackles": 0, "winning_goals": 0, "attempted_passes": 0, "completed_passes": 0, "penalties_conceded": 0, "big_chances_missed": 0, "errors_leading_to_goal": 0, "errors_leading_to_goal_attempt": 0, "tackled": 0, "offside": 0, "target_missed": 0, "fouls": 0, "dribbles": 0, "element": 384, "fixture": 288, "opponent_team": 11}, {"id": 16600, "kickoff_time": "2019-03-09T17:30:00Z", "kickoff_time_formatted": "09 Mar 17:30", "team_h_score": 3, "team_a_score": 1, "was_home": false, "round": 30, "total_points": 0, "value": 42, "transfers_balance": -25, "selected": 2864, "transfers_in": 0, "transfers_out": 25, "loaned_in": 0, "loaned_out": 0, "minutes": 0, "goals_scored": 0, "assists": 0, "clean_sheets": 0, "goals_conceded": 0, "own_goals": 0, "penalties_saved": 0, "penalties_missed": 0, "yellow_cards": 0, "red_cards": 0, "saves": 0, "bonus": 0, "bps": 0, "influence": "0.0", "creativity": "0.0", "threat": "0.0", "ict_index": "0.0", "ea_index": 0, "open_play_crosses": 0, "big_chances_created": 0, "clearances_blocks_interceptions": 0, "recoveries": 0, "key_passes": 0, "tackles": 0, "winning_goals": 0, "attempted_passes": 0, "completed_passes": 0, "penalties_conceded": 0, "big_chances_missed": 0, "errors_leading_to_goal": 0, "errors_leading_to_goal_attempt": 0, "tackled": 0, "offside": 0, "target_missed": 0, "fouls": 0, "dribbles": 0, "element": 384, "fixture": 298, "opponent_team": 13}]}